{
    "records": [
        {
            "id": "rec013Sizh8aRBejZ",
            "fields": {
                "email": "sarka.karlova7@gmail.com",
                "profilePictureUrl": "https://data.cesko.digital/people/sarka-karlova.jpg",
                "name": "Šárka Karlová",
                "Projects": [
                    "recvOO9ssGZZtYGux"
                ]
            },
            "createdTime": "2021-04-08T09:25:08.000Z"
        },
        {
            "id": "rec0ABdJtGIK9AeCB",
            "fields": {
                "email": "romana@cesko.digital",
                "profilePictureUrl": "https://data.cesko.digital/people/romana-pokorna.jpg",
                "name": "Romana Pokorná",
                "company": "Česko.Digital",
                "Projects": [
                    "recX5jS7TTzUxgNbu",
                    "rec4KOruzwIFU8ieR"
                ]
            },
            "createdTime": "2021-04-08T09:30:32.000Z"
        },
        {
            "id": "rec2rVBOmB4pgQAEL",
            "fields": {
                "email": "eva.zehnalkova@cesko.digital",
                "profilePictureUrl": "https://data.cesko.digital/people/eva-zehnalkova.jpg",
                "name": "Eva Zehnálková",
                "company": "Česko.Digital"
            },
            "createdTime": "2021-04-06T08:13:19.000Z"
        },
        {
            "id": "rec2tXP7Cxat1JJMR",
            "fields": {
                "email": "vojtech.petrus@askattest.com",
                "profilePictureUrl": "https://data.cesko.digital/people/vojtech-petrus.jpg",
                "name": "Vojtěch Petrus",
                "Projects": [
                    "recyAlQx0HFH0kW6h"
                ]
            },
            "createdTime": "2021-03-31T12:52:02.000Z"
        },
        {
            "id": "rec4N4PrvAHEddN4u",
            "fields": {
                "email": "katerina.beranova@cesko.digital",
                "profilePictureUrl": "https://data.cesko.digital/people/katerina-beranova.jpg",
                "name": "Kateřina Beranová",
                "Projects": [
                    "recsIWPWTCFAvE2c2"
                ]
            },
            "createdTime": "2021-04-08T09:52:55.000Z"
        },
        {
            "id": "rec4aPaaf2GDZ3VoH",
            "fields": {
                "email": "tomas.walek@cesko.digital",
                "profilePictureUrl": "https://data.cesko.digital/people/tomas-walek.jpg",
                "name": "Tomáš Walek",
                "Projects": [
                    "recH58QD0JhwTis0F"
                ]
            },
            "createdTime": "2021-04-08T09:42:35.000Z"
        },
        {
            "id": "rec5g2kjJCODPpUOI",
            "fields": {
                "email": "jindrich@cesko.digital",
                "profilePictureUrl": "https://data.cesko.digital/people/jindrich-oukropec.jpg",
                "name": "Jindřich Oukropec",
                "company": "Česko.Digital",
                "Projects": [
                    "recyAlQx0HFH0kW6h",
                    "recSci1ztMeeakzg2"
                ]
            },
            "createdTime": "2021-04-08T15:00:39.000Z"
        },
        {
            "id": "rec5i9y2EIaX1ZKD2",
            "fields": {
                "email": "martin.wenisch@cesko.digital ",
                "profilePictureUrl": "https://data.cesko.digital/people/martin-wenisch.jpg",
                "name": "Martin Wenisch"
            },
            "createdTime": "2021-04-06T08:13:19.000Z"
        },
        {
            "id": "rec6MoceaMSaa4BOh",
            "fields": {
                "email": "honza@ovax.cz",
                "profilePictureUrl": "https://data.cesko.digital/people/honza-slavik.jpg",
                "name": "Honza Slavík",
                "Projects": [
                    "recZmB7InVkjYtbnn"
                ]
            },
            "createdTime": "2021-04-08T09:41:43.000Z"
        },
        {
            "id": "rec6hQPrLsA7vVjGD",
            "fields": {
                "email": "eva@cesko.digital",
                "profilePictureUrl": "https://data.cesko.digital/people/eva-pavlikova.jpg",
                "name": "Eva Pavlíková",
                "Projects": [
                    "recDZjnFw8B7jTxdg",
                    "recZmB7InVkjYtbnn",
                    "recAh6CmL9dLySvjH"
                ]
            },
            "createdTime": "2021-02-28T19:21:22.000Z"
        },
        {
            "id": "rec7GkIKStJ4iXgJ6",
            "fields": {
                "email": "sojkaradekk@gmail.com",
                "profilePictureUrl": "https://data.cesko.digital/people/radek-sojka.jpg",
                "name": "Radek Sojka",
                "Projects": [
                    "recH58QD0JhwTis0F"
                ]
            },
            "createdTime": "2021-04-08T09:48:58.000Z"
        },
        {
            "id": "rec8zukUxcKUM0Apk",
            "fields": {
                "email": "radka@cesko.digital",
                "profilePictureUrl": "https://data.cesko.digital/people/radka-horakova.jpg",
                "name": "Radka Horáková",
                "company": "Česko.Digital"
            },
            "createdTime": "2021-04-06T08:13:19.000Z"
        },
        {
            "id": "rec9C0wr25KfWqRUW",
            "fields": {
                "email": "jana@cesko.digital",
                "profilePictureUrl": "https://data.cesko.digital/people/jana-kneschke.jpg",
                "name": "Jana Kneschke",
                "company": "Česko.Digital"
            },
            "createdTime": "2021-04-06T08:13:19.000Z"
        },
        {
            "id": "rec9cgf8d1RK9CJHS",
            "fields": {
                "email": "pavla.kadlecova@otevrenamesta.cz",
                "profilePictureUrl": "https://data.cesko.digital/people/pavla-kadlecova.jpg",
                "name": "Pavla Kadlecová",
                "Projects": [
                    "recIKAscZHA0hVHBX"
                ]
            },
            "createdTime": "2021-04-06T07:53:14.000Z"
        },
        {
            "id": "recA5nftMpxJmwpr4",
            "fields": {
                "email": "zoul@cesko.digital",
                "profilePictureUrl": "https://data.cesko.digital/people/tomas-znamenacek.jpg",
                "name": "Tomáš Znamenáček",
                "company": "Česko.Digital",
                "Events": [
                    "recL6LSVKhgH81MBJ"
                ]
            },
            "createdTime": "2021-06-14T12:38:43.000Z"
        },
        {
            "id": "recAV6IZWuquxQCuZ",
            "fields": {
                "email": "loopolakova@gmail.com",
                "profilePictureUrl": "https://data.cesko.digital/people/lucia-polakova.jpg",
                "name": "Lucia Poláková",
                "Projects": [
                    "recyAlQx0HFH0kW6h"
                ]
            },
            "createdTime": "2021-04-01T11:28:10.000Z"
        },
        {
            "id": "recHnc5hx8wh29zqU",
            "fields": {
                "email": "lucie@cesko.digital",
                "profilePictureUrl": "https://data.cesko.digital/people/lucie-zajickova.jpg",
                "name": "Lucie Zajíčková",
                "company": "Česko.Digital"
            },
            "createdTime": "2021-04-09T13:16:54.000Z"
        },
        {
            "id": "recL8KsRVopRJPiyh",
            "fields": {
                "email": "klara@cesko.digital",
                "profilePictureUrl": "https://data.cesko.digital/people/klara-podpierova.jpg",
                "name": "Klára Podpierová",
                "Projects": [
                    "recsIWPWTCFAvE2c2"
                ]
            },
            "createdTime": "2021-04-08T09:53:18.000Z"
        },
        {
            "id": "recOLDM8bee0EMlKz",
            "fields": {
                "email": "eibl@transparency.cz",
                "profilePictureUrl": "https://data.cesko.digital/people/generic-profile.jpg",
                "name": "Milan Eibl",
                "Projects": [
                    "recJsdOY0oyGO6xxX"
                ]
            },
            "createdTime": "2021-04-08T09:39:34.000Z"
        },
        {
            "id": "recORtmcTpBOIfLJ2",
            "fields": {
                "email": "josef.slerka@gmail.com",
                "profilePictureUrl": "https://data.cesko.digital/people/josef-slerka.jpg",
                "name": "Josef Šlerka",
                "Projects": [
                    "recSci1ztMeeakzg2"
                ]
            },
            "createdTime": "2021-03-31T13:04:24.000Z"
        },
        {
            "id": "recStfHLM7hRGMFFl",
            "fields": {
                "email": "bares.jakub@gmail.com",
                "profilePictureUrl": "https://data.cesko.digital/people/jakub-bares.jpg",
                "name": "Jakub Bareš"
            },
            "createdTime": "2021-03-31T13:04:24.000Z"
        },
        {
            "id": "recTGpmslRgXD65Gv",
            "fields": {
                "email": "petr.kuncl@gmail.com",
                "profilePictureUrl": "https://data.cesko.digital/people/generic-profile.jpg",
                "name": "Petr Kuncl",
                "Projects": [
                    "recSci1ztMeeakzg2"
                ]
            },
            "createdTime": "2021-03-31T13:02:49.000Z"
        },
        {
            "id": "recUAa0VnckxGxdbM",
            "fields": {
                "email": "daniel.urban@cesko.digital ",
                "profilePictureUrl": "https://data.cesko.digital/people/daniel-urban.jpg",
                "name": "Daniel Urban",
                "Projects": [
                    "recxWVIA1Ex40nWi7"
                ]
            },
            "createdTime": "2021-04-08T09:33:27.000Z"
        },
        {
            "id": "recYIWlSDlcXgQ377",
            "fields": {
                "email": "terezia.palascakova@gmail.com",
                "profilePictureUrl": "https://data.cesko.digital/people/terezia-palascakova.jpg",
                "name": "Terézia Palaščáková"
            },
            "createdTime": "2021-03-22T22:16:29.000Z"
        },
        {
            "id": "recaakebNpMz1pj1h",
            "fields": {
                "email": "jiri.kucera@nfnz.cz",
                "profilePictureUrl": "https://data.cesko.digital/people/jiri-kucera.jpg",
                "name": "Jiří Kučera",
                "Projects": [
                    "recSci1ztMeeakzg2"
                ]
            },
            "createdTime": "2021-03-31T13:04:24.000Z"
        },
        {
            "id": "recbKgbPikNgaN3NR",
            "fields": {
                "email": "tomas@sinfin.cz",
                "profilePictureUrl": "https://data.cesko.digital/people/tomas-bajer.jpg",
                "name": "Tomáš Bajer",
                "Projects": [
                    "recJsdOY0oyGO6xxX"
                ]
            },
            "createdTime": "2021-04-08T09:36:19.000Z"
        },
        {
            "id": "recd6cyps6emvcrl8",
            "fields": {
                "email": "jana@cesko.digital",
                "profilePictureUrl": "https://data.cesko.digital/people/jana-kneschke.jpg",
                "name": "Jana Kneschke"
            },
            "createdTime": "2021-03-22T21:09:43.000Z"
        },
        {
            "id": "recd8xvbWp7K1nZn8",
            "fields": {
                "email": "blanka.sigmundova@loono.cz",
                "profilePictureUrl": "https://data.cesko.digital/people/blanka-sigmundova.jpg",
                "name": "Blanka Sigmundová",
                "Projects": [
                    "rec4KOruzwIFU8ieR"
                ]
            },
            "createdTime": "2021-04-09T13:31:08.000Z"
        },
        {
            "id": "recdPMOKc0urpcUiP",
            "fields": {
                "email": "radko@cesko.digital",
                "profilePictureUrl": "https://data.cesko.digital/people/radko-jirousek.jpg",
                "name": "Radko Jiroušek",
                "company": "Česko.Digital",
                "Projects": [
                    "recZmB7InVkjYtbnn"
                ]
            },
            "createdTime": "2021-04-06T08:13:19.000Z"
        },
        {
            "id": "receJeHvUSgZFvbCt",
            "fields": {
                "email": "radka.stekla@cesko.digital",
                "profilePictureUrl": "https://data.cesko.digital/people/radka-stekla.jpg",
                "name": "Radka Steklá",
                "Projects": [
                    "recvOO9ssGZZtYGux"
                ]
            },
            "createdTime": "2021-04-08T09:24:01.000Z"
        },
        {
            "id": "recf6EM1qZxTTFkA0",
            "fields": {
                "email": "gabriela@cesko.digital",
                "profilePictureUrl": "https://data.cesko.digital/people/gabriela-chladilova.jpg",
                "name": "Gabriela Chladilová",
                "company": "Česko.Digital",
                "Projects": [
                    "recsIWPWTCFAvE2c2"
                ]
            },
            "createdTime": "2021-04-08T09:51:57.000Z"
        },
        {
            "id": "recfTQpPu9LYMIAps",
            "fields": {
                "email": "anezka@cesko.digital",
                "profilePictureUrl": "https://data.cesko.digital/people/anezka-muller.jpg",
                "name": "Anežka Müller",
                "company": "Česko.Digital",
                "Projects": [
                    "recsIWPWTCFAvE2c2"
                ]
            },
            "createdTime": "2021-04-08T09:51:08.000Z"
        },
        {
            "id": "recfv4fZJP4dBtB85",
            "fields": {
                "email": "sarka.rauchova@gmail.com",
                "profilePictureUrl": "https://data.cesko.digital/people/sarka-rauchova.jpg",
                "name": "Šárka Rauchová",
                "Projects": [
                    "recSci1ztMeeakzg2"
                ]
            },
            "createdTime": "2021-03-31T13:02:54.000Z"
        },
        {
            "id": "recheJ92XChLaVlsr",
            "fields": {
                "email": "katerina@cesko.digital",
                "profilePictureUrl": "https://data.cesko.digital/people/katerina-kocianova.jpg",
                "name": "Kateřina Kocianová",
                "company": "Česko.Digital",
                "Projects": [
                    "recAh6CmL9dLySvjH",
                    "recvOO9ssGZZtYGux",
                    "recxWVIA1Ex40nWi7",
                    "recH58QD0JhwTis0F",
                    "recIKAscZHA0hVHBX"
                ]
            },
            "createdTime": "2021-04-06T08:13:19.000Z"
        },
        {
            "id": "recjT3JYlbBOJaUfn",
            "fields": {
                "email": "michal.vorac@gmail.com",
                "profilePictureUrl": "https://data.cesko.digital/people/michal-vorac.jpg",
                "name": "Michal Voráč",
                "Projects": [
                    "recX5jS7TTzUxgNbu"
                ]
            },
            "createdTime": "2021-04-08T09:29:51.000Z"
        },
        {
            "id": "recjz4dPPH7bqa1l1",
            "fields": {
                "email": "sandra@vyluka.org",
                "profilePictureUrl": "https://data.cesko.digital/people/sandra-feyglova.jpg",
                "name": "Sandra Ort Feyglová",
                "Projects": [
                    "recX5jS7TTzUxgNbu"
                ]
            },
            "createdTime": "2021-04-08T09:26:02.000Z"
        },
        {
            "id": "recl1mVQmM6euzmua",
            "fields": {
                "email": "barbora.petrikova@cesko.digital",
                "profilePictureUrl": "https://data.cesko.digital/people/bara_petrikova.jpg",
                "name": "Barbora Petříková",
                "Projects": [
                    "recsIWPWTCFAvE2c2"
                ]
            },
            "createdTime": "2021-06-07T13:05:50.000Z"
        },
        {
            "id": "recmtJGXYYovYzA5O",
            "fields": {
                "email": "jakub@cesko.digital",
                "profilePictureUrl": "https://data.cesko.digital/people/jakub-nesetril.jpg",
                "name": "Jakub Nešetřil",
                "company": "Česko.Digital",
                "Projects": [
                    "recJsdOY0oyGO6xxX"
                ]
            },
            "createdTime": "2021-04-06T08:13:19.000Z"
        },
        {
            "id": "recni1NCgzKZvdnhN",
            "fields": {
                "email": "petra.fritsch@cesko.digital ",
                "profilePictureUrl": "https://data.cesko.digital/people/petra-fritsch.jpg",
                "name": "Petra Fritsch",
                "Projects": [
                    "recxWVIA1Ex40nWi7"
                ]
            },
            "createdTime": "2021-04-08T09:32:14.000Z"
        },
        {
            "id": "recq96qTt3FqC7Mt6",
            "fields": {
                "email": "jana@vyluka.org",
                "profilePictureUrl": "https://data.cesko.digital/people/jana-vyluka.jpg",
                "name": "Jana Fryzelková",
                "Projects": [
                    "recX5jS7TTzUxgNbu"
                ]
            },
            "createdTime": "2021-04-08T09:28:05.000Z"
        },
        {
            "id": "recqScHnCjZpuSLAm",
            "fields": {
                "email": "katerina.alturbanova@cesko.digital",
                "profilePictureUrl": "https://data.cesko.digital/people/katka_alturbanova.jpg",
                "name": "Kateřina Alturbanová",
                "Projects": [
                    "recsIWPWTCFAvE2c2"
                ]
            },
            "createdTime": "2021-06-07T13:01:13.000Z"
        },
        {
            "id": "recshDKxv31hsdyX4",
            "fields": {
                "email": "zuzana.fialova@cesko.digital",
                "profilePictureUrl": "https://data.cesko.digital/people/zuzana-fialova.jpg",
                "name": "Zuzana Fialová",
                "Projects": [
                    "recAh6CmL9dLySvjH"
                ]
            },
            "createdTime": "2021-04-08T09:05:28.000Z"
        },
        {
            "id": "recuJsidR6ztcjiiC",
            "fields": {
                "email": "radka@cesko.digital",
                "profilePictureUrl": "https://data.cesko.digital/people/radka-horakova.jpg",
                "name": "Radka Horáková"
            },
            "createdTime": "2021-03-22T21:06:00.000Z"
        },
        {
            "id": "recwOLHFJUPCoPnLX",
            "fields": {
                "email": "kalusovaadela@gmail.com",
                "profilePictureUrl": "https://data.cesko.digital/people/adela-kalusova.jpg",
                "name": "Adéla Kalusová",
                "Projects": [
                    "recZmB7InVkjYtbnn",
                    "recIKAscZHA0hVHBX",
                    "rec4KOruzwIFU8ieR"
                ]
            },
            "createdTime": "2021-04-06T08:13:19.000Z"
        },
        {
            "id": "recxcXvq41ulDzNEz",
            "fields": {
                "email": "karolina.mikova@getmanta.com",
                "profilePictureUrl": "https://data.cesko.digital/people/karolina-mikova.jpg",
                "name": "Karolina Míková",
                "Projects": [
                    "recIKAscZHA0hVHBX"
                ]
            },
            "createdTime": "2021-04-06T08:13:19.000Z"
        },
        {
            "id": "recxnKoDo13IRSbGV",
            "fields": {
                "email": "tereza@cesko.digital",
                "profilePictureUrl": "https://data.cesko.digital/people/tereza-polednova.jpg",
                "name": "Tereza Polednová",
                "Projects": [
                    "recyAlQx0HFH0kW6h"
                ]
            },
            "createdTime": "2021-04-01T11:28:25.000Z"
        }
    ]
}